LICENSE
MANIFEST.in
README.md
setup.py
django_passkeys.egg-info/PKG-INFO
django_passkeys.egg-info/SOURCES.txt
django_passkeys.egg-info/dependency_links.txt
django_passkeys.egg-info/not-zip-safe
django_passkeys.egg-info/requires.txt
django_passkeys.egg-info/top_level.txt
passkeys/FIDO2.py
passkeys/__init__.py
passkeys/backend.py
passkeys/models.py
passkeys/urls.py
passkeys/views.py
passkeys/migrations/0001_initial.py
passkeys/migrations/__init__.py
passkeys/static/passkeys/css/bootstrap-toggle.min.css
passkeys/static/passkeys/imgs/FIDO-Passkey_Icon-White.png
passkeys/static/passkeys/js/base64url.js
passkeys/static/passkeys/js/bootstrap-toggle.min.js
passkeys/static/passkeys/js/helpers.js
passkeys/templates/PassKeys.html
passkeys/templates/PassKeys_base.html
passkeys/templates/check_passkeys.js
passkeys/templates/modal.html
passkeys/templates/passkeys.js